ivim/__init__.py
ivim/constants.py
ivim/fit.py
ivim/misc.py
ivim/models.py
ivim/optimize.py
ivim/sim.py
ivim/io/__init__.py
ivim/io/base.py
ivim/io/philips.py
ivim/preproc/__init__.py
ivim/preproc/base.py
ivim/preproc/signal_drift.py
ivim/seq/__init__.py
ivim/seq/fwf.py
ivim/seq/lte.py
ivim_mri-1.0.1.dist-info/METADATA
ivim_mri-1.0.1.dist-info/WHEEL
ivim_mri-1.0.1.dist-info/licenses/LICENSE
ivim_mri-1.0.1.dist-info/RECORD
