Metadata-Version: 2.4
Name: ivim-mri
Version: 1.0.1
Summary: Tools related to Intravoxel Incoherent Motion (IVIM) modeling of diffusion MRI data
Project-URL: Homepage, https://ivim.readthedocs.io/
Author-email: Oscar Jalnefjord <oscar.jalnefjord@gu.se>
License: BSD 3-Clause License
License-File: LICENSE
Keywords: IVIM,MRI,diffusion,intravoxel incoherent motion,perfusion,python
Classifier: Intended Audience :: Developers
Classifier: Intended Audience :: Science/Research
Classifier: Operating System :: OS Independent
Classifier: Programming Language :: Python
Classifier: Programming Language :: Python :: 3
Classifier: Topic :: Scientific/Engineering
Requires-Python: >=3.10
Requires-Dist: nibabel
Requires-Dist: numpy<2
Requires-Dist: scipy
Provides-Extra: docs
Requires-Dist: ipykernel; extra == 'docs'
Requires-Dist: matplotlib; extra == 'docs'
Requires-Dist: nbsphinx; extra == 'docs'
Requires-Dist: pandoc; extra == 'docs'
Requires-Dist: sphinx; extra == 'docs'
Requires-Dist: sphinx-copybutton; extra == 'docs'
Requires-Dist: sphinx-rtd-theme; extra == 'docs'
Provides-Extra: tests
Requires-Dist: pytest; extra == 'tests'
